rapidtables/__init__.py
rapidtables-0.1.12.dist-info/licenses/LICENSE
rapidtables-0.1.12.dist-info/METADATA
rapidtables-0.1.12.dist-info/WHEEL
rapidtables-0.1.12.dist-info/top_level.txt
rapidtables-0.1.12.dist-info/RECORD
