Metadata-Version: 2.4
Name: rapidtables
Version: 0.1.12
Summary: Format/create and print tables from lists of dicts
Author-email: Altertech <div@altertech.com>
License-Expression: MIT
Project-URL: Source, https://github.com/alttch/rapidtables
Project-URL: Issues, https://github.com/alttch/rapidtables/issues
Classifier: Programming Language :: Python :: 2
Classifier: Programming Language :: Python :: 3
Classifier: Topic :: Software Development :: Libraries
Classifier: Topic :: Text Processing
Classifier: Topic :: Text Processing :: Markup
License-File: LICENSE
Dynamic: license-file
